MANIFEST.in
README.rst
az
requirements.txt
setup.py
azcat/__init__.py
azcat/guess_ext.py
azcat/main.py
azcat/pretty_print.py
azcat.egg-info/PKG-INFO
azcat.egg-info/SOURCES.txt
azcat.egg-info/dependency_links.txt
azcat.egg-info/requires.txt
azcat.egg-info/top_level.txt
azcat/formatters/__init__.py
azcat/formatters/csv.py
azcat/formatters/html.py
azcat/formatters/json.py
azcat/highlighters/__init__.py
azcat/highlighters/md.py