Metadata-Version: 1.1
Name: azcat
Version: 1.0.5
Summary: A alternative to cat(1); specialized for printing files
Home-page: http://github.com/nuta/azcat
Author: Seiya Nuta
Author-email: nuta@seiya.me
License: UNKNOWN
Platform: UNKNOWN
Classifier: Development Status :: 5 - Production/Stable
Classifier: Environment :: Console
Classifier: License :: Public Domain
Classifier: Operating System :: POSIX
Classifier: Topic :: Utilities
